mddocx/__init__.py
mddocx/cli.py
mddocx/converter/__init__.py
mddocx/converter/base.py
mddocx/converter/elements/__init__.py
mddocx/converter/elements/base.py
mddocx/converter/elements/blockquote.py
mddocx/converter/elements/code.py
mddocx/converter/elements/heading.py
mddocx/converter/elements/hr.py
mddocx/converter/elements/html.py
mddocx/converter/elements/image.py
mddocx/converter/elements/links.py
mddocx/converter/elements/list.py
mddocx/converter/elements/table.py
mddocx/converter/elements/task_list.py
mddocx/converter/elements/text.py
mddocx/webui/README.md
mddocx/webui/__init__.py
mddocx/webui/app.py
mddocx/webui/config.py
mddocx/webui/start_webui.py
mddocx/webui/static/css/styles.css
mddocx/webui/static/js/app.js
mddocx/webui/templates/base.html
mddocx/webui/templates/index.html
mddocx/webui/templates/preview.html
mddocx/webui/tests/__init__.py
mddocx/webui/tests/test_basic.py
mddocx-0.4.3.dist-info/licenses/LICENSE
mddocx-0.4.3.dist-info/METADATA
mddocx-0.4.3.dist-info/WHEEL
mddocx-0.4.3.dist-info/entry_points.txt
mddocx-0.4.3.dist-info/top_level.txt
mddocx-0.4.3.dist-info/RECORD
