Metadata-Version: 2.4
Name: mddocx
Version: 0.4.3
Summary: 一个功能强大的 Markdown 转 DOCX 文档转换工具
Author-email: "jw.zhou" <zhou24388@163.com>
License: MIT
Project-URL: Homepage, https://github.com/wangqiqi/md2docx
Project-URL: Repository, https://github.com/wangqiqi/md2docx
Project-URL: Documentation, https://github.com/wangqiqi/md2docx#readme
Project-URL: Issues, https://github.com/wangqiqi/md2docx/issues
Keywords: markdown,docx,converter,document,python
Classifier: Development Status :: 4 - Beta
Classifier: Intended Audience :: Developers
Classifier: License :: OSI Approved :: MIT License
Classifier: Programming Language :: Python :: 3
Classifier: Programming Language :: Python :: 3.8
Classifier: Programming Language :: Python :: 3.9
Classifier: Programming Language :: Python :: 3.10
Classifier: Programming Language :: Python :: 3.11
Classifier: Topic :: Text Processing :: Markup
Classifier: Topic :: Utilities
Requires-Python: >=3.8
License-File: LICENSE
Requires-Dist: python-docx>=0.8.11
Requires-Dist: markdown-it-py>=2.1.0
Requires-Dist: flask>=2.0.0
Requires-Dist: werkzeug>=2.0.0
Provides-Extra: dev
Requires-Dist: pytest>=7.0.0; extra == "dev"
Requires-Dist: pytest-cov>=4.0.0; extra == "dev"
Requires-Dist: coverage>=7.0.0; extra == "dev"
Requires-Dist: flake8>=6.0.0; extra == "dev"
Requires-Dist: black>=23.0.0; extra == "dev"
Requires-Dist: mypy>=1.0.0; extra == "dev"
Requires-Dist: isort>=5.12.0; extra == "dev"
Requires-Dist: build>=1.0.0; extra == "dev"
Requires-Dist: twine>=4.0.0; extra == "dev"
Provides-Extra: docs
Requires-Dist: sphinx>=5.0.0; extra == "docs"
Requires-Dist: sphinx-rtd-theme>=1.2.0; extra == "docs"
Dynamic: license-file
